{
  "type": "minecraft:chest",
  "pools": [
    {
      "name": "bedrockminer",
      "rolls": {
        "min": 0,
        "max": 3
      },
      "entries": [

        {
          "type": "minecraft:item",
          "name": "bedrockminer:bedrock_chunk",
          "weight": 5,
          "functions": [
            {
              "function": "minecraft:set_count",
              "count": {
                "min": 1,
                "max": 3
              }
            }
          ]
        }

      ]
    }
  ]
}